<beans xmlns="http://www.springframework.org/schema/beans"
	xmlns:batch="http://www.springframework.org/schema/batch" xmlns:xsi="http://www.w3.org/2001/XMLSchema-instance"
	xmlns:context="http://www.springframework.org/schema/context"
	xmlns:jdbc="http://www.springframework.org/schema/jdbc"
	xsi:schemaLocation="
           http://www.springframework.org/schema/beans http://www.springframework.org/schema/beans/spring-beans.xsd
           http://www.springframework.org/schema/context http://www.springframework.org/schema/context/spring-context.xsd
           http://www.springframework.org/schema/batch http://www.springframework.org/schema/batch/spring-batch.xsd
           http://www.springframework.org/schema/jdbc http://www.springframework.org/schema/jdbc/spring-jdbc.xsd">

	<context:annotation-config />

	<batch:job id="estrazione-dipendenti-con-contratto">
		<batch:step id="main">
			<batch:tasklet>
				<batch:chunk reader="itemReader" processor="itemProcessor"
					writer="itemWriter" commit-interval="100" />
			</batch:tasklet>
		</batch:step>
	</batch:job>

	<bean id="itemReader"
		class="org.springframework.batch.item.database.JdbcCursorItemReader">
		<property name="dataSource" ref="dataSource" />
		<property name="sql">
			<value>
				SELECT * FROM DIPENDENTI ORDER BY COGNOME
			</value>
		</property>
		<property name="rowMapper">
			<bean class="org.springframework.jdbc.core.BeanPropertyRowMapper">
				<constructor-arg name="mappedClass" value="com.acme.hr.dto.Dipendente" />
			</bean>
		</property>
	</bean>

	<bean class="com.acme.hr.prova.batch.estrazionedipendenticoncontratto.TrasformazioneStringhe" />
	
	<bean id="itemProcessor"
		class="com.acme.hr.prova.batch.estrazionedipendenticoncontratto.EstrazioneDipendentiConContrattoProcessor" />

	<bean id="itemWriter"
		class="org.springframework.batch.item.support.CompositeItemWriter">
		<property name="delegates">
			<list>
				<bean class="org.springframework.batch.item.file.FlatFileItemWriter">
					<property name="resource"
						value="file:estrazione-dipendenti-con-tipo-contratto.csv" />
					<property name="lineAggregator">
						<bean
							class="org.springframework.batch.item.file.transform.DelimitedLineAggregator">
							<property name="delimiter" value="," />
							<property name="fieldExtractor">
								<bean
									class="org.springframework.batch.item.file.transform.BeanWrapperFieldExtractor">
									<property name="names" value="cognome,nome,descrizioneTipoContratto" />
								</bean>
							</property>
						</bean>
					</property>
				</bean>
			</list>
		</property>
	</bean>

	<bean id="jobLauncher"
		class="org.springframework.batch.core.launch.support.SimpleJobLauncher">
		<property name="jobRepository" ref="jobRepository" />
	</bean>

	<bean id="jobRepository"
		class="org.springframework.batch.core.repository.support.MapJobRepositoryFactoryBean" />

	<bean id="transactionManager"
		class="org.springframework.batch.support.transaction.ResourcelessTransactionManager" />

	<jdbc:embedded-database id="dataSource" type="H2">
		<jdbc:script location="classpath:sql/db-schema.sql" />
		<jdbc:script location="classpath:sql/db-test-data.sql" />
	</jdbc:embedded-database>

</beans>